feedancy/__init__.py
feedancy/apis/__init__.py
feedancy/apis/api/__init__.py
feedancy/apis/api/api.py
feedancy/apis/api/api_v1_activitysphere_create.py
feedancy/apis/api/api_v1_activitysphere_destroy.py
feedancy/apis/api/api_v1_activitysphere_retrieve.py
feedancy/apis/api/api_v1_activitysphere_retrieve_2.py
feedancy/apis/api/api_v1_activitysphere_update.py
feedancy/apis/api/api_v1_city_create.py
feedancy/apis/api/api_v1_city_destroy.py
feedancy/apis/api/api_v1_city_retrieve.py
feedancy/apis/api/api_v1_city_retrieve_2.py
feedancy/apis/api/api_v1_city_update.py
feedancy/apis/api/api_v1_company_create.py
feedancy/apis/api/api_v1_company_destroy.py
feedancy/apis/api/api_v1_company_retrieve.py
feedancy/apis/api/api_v1_company_retrieve_2.py
feedancy/apis/api/api_v1_company_update.py
feedancy/apis/api/api_v1_companycity_create.py
feedancy/apis/api/api_v1_companycity_destroy.py
feedancy/apis/api/api_v1_companycity_retrieve.py
feedancy/apis/api/api_v1_companycity_retrieve_2.py
feedancy/apis/api/api_v1_companycity_update.py
feedancy/apis/api/api_v1_contact_create.py
feedancy/apis/api/api_v1_contact_destroy.py
feedancy/apis/api/api_v1_contact_retrieve.py
feedancy/apis/api/api_v1_contact_retrieve_2.py
feedancy/apis/api/api_v1_contact_update.py
feedancy/apis/api/api_v1_country_create.py
feedancy/apis/api/api_v1_country_destroy.py
feedancy/apis/api/api_v1_country_retrieve.py
feedancy/apis/api/api_v1_country_retrieve_2.py
feedancy/apis/api/api_v1_country_update.py
feedancy/apis/api/api_v1_currency_create.py
feedancy/apis/api/api_v1_currency_destroy.py
feedancy/apis/api/api_v1_currency_retrieve.py
feedancy/apis/api/api_v1_currency_retrieve_2.py
feedancy/apis/api/api_v1_currency_update.py
feedancy/apis/api/api_v1_internship_create.py
feedancy/apis/api/api_v1_internship_destroy.py
feedancy/apis/api/api_v1_internship_list.py
feedancy/apis/api/api_v1_internship_retrieve.py
feedancy/apis/api/api_v1_internship_update.py
feedancy/apis/api/api_v1_internshipcontact_create.py
feedancy-0.1.31.dist-info/METADATA
feedancy-0.1.31.dist-info/WHEEL
feedancy-0.1.31.dist-info/RECORD
