Metadata-Version: 2.1
Name: feedancy
Version: 0.1.31
Summary: сервис по сбору вакансий
License: MIT
Author: Alexey Ostanin
Author-email: aostaninn@gmal.com
Requires-Python: >=3.10
Classifier: License :: OSI Approved :: MIT License
Classifier: Programming Language :: Python :: 3
Classifier: Programming Language :: Python :: 3.10
Classifier: Programming Language :: Python :: 3.11
Classifier: Programming Language :: Python :: 3.12
Requires-Dist: bs4 (>=0.0.1)
Requires-Dist: requests (>=2.31)
